pi4ioe5v9xxxx_drv/__init__.py
pi4ioe5v9xxxx_drv/pi4ioe5v9xxxx_drv.py
pi4ioe5v9xxxx_drv-0.0.4.dist-info/LICENSE
pi4ioe5v9xxxx_drv-0.0.4.dist-info/METADATA
pi4ioe5v9xxxx_drv-0.0.4.dist-info/WHEEL
pi4ioe5v9xxxx_drv-0.0.4.dist-info/top_level.txt
pi4ioe5v9xxxx_drv-0.0.4.dist-info/RECORD
